anon_python_sdk/__init__.py
anon_python_sdk/anon_runner.py
anon_python_sdk/control_client.py
anon_python_sdk/exceptions.py
anon_python_sdk/models.py
anon_python_sdk/socks_client.py
anon_python_sdk-0.0.5.dist-info/METADATA
anon_python_sdk-0.0.5.dist-info/WHEEL
anon_python_sdk-0.0.5.dist-info/top_level.txt
anon_python_sdk-0.0.5.dist-info/RECORD
