Metadata-Version: 2.1
Name: anon-python-sdk
Version: 0.0.5
Summary: Python SDK for Anon
Classifier: Programming Language :: Python :: 3
Classifier: License :: OSI Approved :: MIT License
Classifier: Operating System :: OS Independent
Requires-Python: >=3.6
Requires-Dist: requests[socks]
Requires-Dist: stem
